[{"id":"1298939449371004979","channel_id":"1298618254381809745","author":{"id":"414288504550588438","username":"jamie0773","avatar":"883e1b28bd08036a951bf1bedd781e87","discriminator":"0","public_flags":0,"flags":0,"banner":null,"accent_color":null,"global_name":"Jamie","avatar_decoration_data":null,"collectibles":null,"display_name_styles":null,"banner_color":null,"clan":null,"primary_guild":null},"content":"I would affirm that yes, the description of something in our ideas or knowledge is not the thing. We might say \"I hate this person\" or \"I love this apple pie\" but then the thing or another person is right in front of us and it defies description because everyone is now experiencing it first hand. \n\nI don't mean to over-reach, but the point I wanted to previously mention (not that you are asking specifically), is that it is possible to operate psychologically without the use of a personal psychological model of reality. You can simply operate in relationship to exactly what is currently occurring, and nothing else it neccessary.","timestamp":"2024-10-24T09:21:37.858000+00:00","edited_timestamp":"2024-10-24T09:22:22.632000+00:00","tts":false,"mention_everyone":false,"mentions":[{"id":"1264037351408144497","username":"arrryan0599","avatar":"51dbde70f92b843c858e25e03310e4ca","discriminator":"0","public_flags":0,"flags":0,"banner":null,"accent_color":null,"global_name":"Arrryan","avatar_decoration_data":{"asset":"a_e08b43c436272bc2c1e6ae85e71ab884","sku_id":"1402472280596152340","expires_at":null},"collectibles":{"nameplate":{"sku_id":"1377377712028516443","asset":"nameplates/nameplates_v2/spirit_moon/","label":"COLLECTIBLES_NAMEPLATES_V2_SPIRIT_MOON_A11Y","palette":"violet"}},"display_name_styles":null,"banner_color":null,"clan":null,"primary_guild":null}],"attachments":[],"embeds":[],"pinned":false,"type":19,"message_reference":{"type":0,"channel_id":"1298618254381809745","message_id":"1298932824786604033","guild_id":"1129343306485215342"},"flags":0,"components":[],"position":15,"userName":"jamie0773"},{"id":"1298932523228991509","channel_id":"1298618254381809745","author":{"id":"414288504550588438","username":"jamie0773","avatar":"883e1b28bd08036a951bf1bedd781e87","discriminator":"0","public_flags":0,"flags":0,"banner":null,"accent_color":null,"global_name":"Jamie","avatar_decoration_data":null,"collectibles":null,"display_name_styles":null,"banner_color":null,"clan":null,"primary_guild":null},"content":"*Going down this lane of giving definitions and meanings we wud kinda arive at it's meaningless as it's just a random thing that doesn't actually mean anything but at the same time we intuitively know it to be something, whoose knowing isn't captured in thoughts, mind.*\n\nI am not trying to be difficult, I straightforwardly don't understand what you're trying to communicate. I'm very happy to respond and will be here to reply, but I don't at grasp what you're trying to say.","timestamp":"2024-10-24T08:54:06.537000+00:00","edited_timestamp":"2024-10-24T08:54:32.389000+00:00","tts":false,"mention_everyone":false,"mentions":[{"id":"1264037351408144497","username":"arrryan0599","avatar":"51dbde70f92b843c858e25e03310e4ca","discriminator":"0","public_flags":0,"flags":0,"banner":null,"accent_color":null,"global_name":"Arrryan","avatar_decoration_data":{"asset":"a_e08b43c436272bc2c1e6ae85e71ab884","sku_id":"1402472280596152340","expires_at":null},"collectibles":{"nameplate":{"sku_id":"1377377712028516443","asset":"nameplates/nameplates_v2/spirit_moon/","label":"COLLECTIBLES_NAMEPLATES_V2_SPIRIT_MOON_A11Y","palette":"violet"}},"display_name_styles":null,"banner_color":null,"clan":null,"primary_guild":null}],"attachments":[],"embeds":[],"pinned":false,"type":19,"message_reference":{"type":0,"channel_id":"1298618254381809745","message_id":"1298931220696137758","guild_id":"1129343306485215342"},"flags":0,"components":[],"position":10,"userName":"jamie0773"},{"id":"1298930376009580545","channel_id":"1298618254381809745","author":{"id":"414288504550588438","username":"jamie0773","avatar":"883e1b28bd08036a951bf1bedd781e87","discriminator":"0","public_flags":0,"flags":0,"banner":null,"accent_color":null,"global_name":"Jamie","avatar_decoration_data":null,"collectibles":null,"display_name_styles":null,"banner_color":null,"clan":null,"primary_guild":null},"content":"Can you clarify what you mean exactly? My understanding is that you are questioning exactly what is the emotional relationship between a self-concept (Me) and what I've referred to as a self-image?","timestamp":"2024-10-24T08:45:34.600000+00:00","edited_timestamp":null,"tts":false,"mention_everyone":false,"mentions":[{"id":"1264037351408144497","username":"arrryan0599","avatar":"51dbde70f92b843c858e25e03310e4ca","discriminator":"0","public_flags":0,"flags":0,"banner":null,"accent_color":null,"global_name":"Arrryan","avatar_decoration_data":{"asset":"a_e08b43c436272bc2c1e6ae85e71ab884","sku_id":"1402472280596152340","expires_at":null},"collectibles":{"nameplate":{"sku_id":"1377377712028516443","asset":"nameplates/nameplates_v2/spirit_moon/","label":"COLLECTIBLES_NAMEPLATES_V2_SPIRIT_MOON_A11Y","palette":"violet"}},"display_name_styles":null,"banner_color":null,"clan":null,"primary_guild":null}],"attachments":[],"embeds":[],"pinned":false,"type":19,"message_reference":{"type":0,"channel_id":"1298618254381809745","message_id":"1298618254381809745","guild_id":"1129343306485215342"},"flags":0,"components":[],"position":1,"userName":"jamie0773"}]